crf/__init__.py
crf/crf.py
crf/utils.py
pytorch_text_crf-0.1.dist-info/LICENSE
pytorch_text_crf-0.1.dist-info/METADATA
pytorch_text_crf-0.1.dist-info/WHEEL
pytorch_text_crf-0.1.dist-info/top_level.txt
pytorch_text_crf-0.1.dist-info/RECORD
