Metadata-Version: 2.1
Name: pytorch-text-crf
Version: 0.1
Summary: A simple crf module written in pytorch. The implementation is based                https://github.com/allenai/allennlp/blob/master/allennlp/modules/conditional_random_field.py
Home-page: https://github.com/iamsimha/pytorch-text-crf
Author: iamsimha
Author-email: jayasimhatlr@gmail.com
License: Apache License, Version 2.0
Platform: UNKNOWN
Classifier: License :: OSI Approved :: Apache Software License
Classifier: Programming Language :: Python :: 3
Classifier: Programming Language :: Python :: 3.7
Requires-Dist: torch
